{"stats":{"minecraft:used":{"gilded_doom:gilded_banisher":12},"minecraft:killed":{"minecraft:creeper":1,"minecraft:zombie":2},"minecraft:custom":{"minecraft:jump":77,"minecraft:time_since_rest":3000,"minecraft:damage_dealt":841,"minecraft:crouch_one_cm":93,"minecraft:sprint_one_cm":2582,"minecraft:play_time":3000,"minecraft:time_since_death":3000,"minecraft:walk_one_cm":5141,"minecraft:sneak_time":63,"minecraft:total_world_time":3220,"minecraft:mob_kills":3,"minecraft:fly_one_cm":17100},"minecraft:picked_up":{"minecraft:rotten_flesh":2,"minecraft:gunpowder":2}},"DataVersion":3120}